rfexplorerDetailedScan/__init__.py
rfexplorerDetailedScan/py.typed
rfexplorerDetailedScan/rfexplorerDetailedScan.py
rfexplorerDetailedScan/scanner.py
rfexplorer_detailed_scan-0.0.5.dist-info/LICENSE.txt
rfexplorer_detailed_scan-0.0.5.dist-info/METADATA
rfexplorer_detailed_scan-0.0.5.dist-info/WHEEL
rfexplorer_detailed_scan-0.0.5.dist-info/entry_points.txt
rfexplorer_detailed_scan-0.0.5.dist-info/top_level.txt
rfexplorer_detailed_scan-0.0.5.dist-info/RECORD
