Metadata-Version: 2.2
Name: rfexplorer-detailed-scan
Version: 0.0.5
Summary: Scans broad frequency bands on an RF Explorer with lower effective resolution bandwidth, saving scan data to a file
Author-email: Matt Kupferman <matt@kupferman.net>
Maintainer-email: Matt Kupferman <matt@kupferman.net>
License: MIT License
Project-URL: Homepage, https://github.com/mkupferman/rfexplorer-detailed-scan
Classifier: Programming Language :: Python :: 3
Classifier: License :: OSI Approved :: MIT License
Classifier: Operating System :: OS Independent
Classifier: Intended Audience :: End Users/Desktop
Classifier: Development Status :: 4 - Beta
Requires-Python: >=3.11
License-File: LICENSE.txt
Requires-Dist: RFExplorer>=1.33.2106.3
Requires-Dist: Click
Provides-Extra: dev
Requires-Dist: black; extra == "dev"
Provides-Extra: validate
Requires-Dist: mypy; extra == "validate"
